hsr_getyundata_v1/__init__.py
hsr_getyundata_v1-0.2.1.dist-info/METADATA
hsr_getyundata_v1-0.2.1.dist-info/WHEEL
hsr_getyundata_v1-0.2.1.dist-info/entry_points.txt
hsr_getyundata_v1-0.2.1.dist-info/top_level.txt
hsr_getyundata_v1-0.2.1.dist-info/RECORD
