Metadata-Version: 2.4
Name: hsr_getyundata_v1
Version: 0.2.1
Summary: HSR 云雨平台数据获取 MCP 工具 - 用于获取和对比 CVM 性能测试报告
Requires-Python: >=3.11
Requires-Dist: mcp[cli]>=1.0.0
Requires-Dist: requests>=2.28.0
